{
  "resourceType": "Patient",
  "id": "19990000000682",
  "extension": [
    {
      "url": "https://bluebutton.cms.gov/resources/variables/race",
      "valueCoding": {
        "system": "https://bluebutton.cms.gov/resources/variables/race",
        "code": "1",
        "display": "White"
      }
    }
  ],
  "identifier": [
    {
      "system": "http://bluebutton.cms.hhs.gov/identifier#bene_id",
      "value": "19990000000682"
    },
    {
      "system": "http://bluebutton.cms.hhs.gov/identifier#hicnHash",
      "value": "b801f6e0ed5e2127dba6a707f23fb88139c1108bc7b035b5ee58a5661eb97d94"
    }
  ],
  "name": [
    {
      "use": "usual",
      "family": "Doe",
      "given": [
        "Jane",
        "X"
      ]
    }
  ],
  "gender": "unknown",
  "birthDate": "1999-06-01",
  "address": [
    {
      "district": "999",
      "state": "33",
      "postalCode": "99999"
    }
  ]
}