{
  "resourceType": "Patient",
  "id": "19990000000770",
  "extension": [
    {
      "url": "https://bluebutton.cms.gov/resources/variables/race",
      "valueCoding": {
        "system": "https://bluebutton.cms.gov/resources/variables/race",
        "code": "5",
        "display": "Hispanic"
      }
    }
  ],
  "identifier": [
    {
      "system": "http://bluebutton.cms.hhs.gov/identifier#bene_id",
      "value": "19990000000770"
    },
    {
      "system": "http://bluebutton.cms.hhs.gov/identifier#hicnHash",
      "value": "fd44f1bd379650c2d2cda9566a19d921f859fcfd124d022272d9f7ae304dbebc"
    }
  ],
  "name": [
    {
      "use": "usual",
      "family": "Doe",
      "given": [
        "Jane",
        "X"
      ]
    }
  ],
  "gender": "unknown",
  "birthDate": "1999-06-01",
  "address": [
    {
      "district": "999",
      "state": "33",
      "postalCode": "99999"
    }
  ]
}