{
  "resourceType": "Patient",
  "id": "19990000000440",
  "extension": [
    {
      "url": "https://bluebutton.cms.gov/resources/variables/race",
      "valueCoding": {
        "system": "https://bluebutton.cms.gov/resources/variables/race",
        "code": "1",
        "display": "White"
      }
    }
  ],
  "identifier": [
    {
      "system": "http://bluebutton.cms.hhs.gov/identifier#bene_id",
      "value": "19990000000440"
    },
    {
      "system": "http://bluebutton.cms.hhs.gov/identifier#hicnHash",
      "value": "5bb470a31140bc866fde7a7afe674341b0d32fd11157bcb5776b0dbbdcfaba55"
    }
  ],
  "name": [
    {
      "use": "usual",
      "family": "Doe",
      "given": [
        "John",
        "X"
      ]
    }
  ],
  "gender": "unknown",
  "birthDate": "1999-06-01",
  "address": [
    {
      "district": "999",
      "state": "10",
      "postalCode": "99999"
    }
  ]
}