{
  "resourceType": "Patient",
  "id": "19990000000162",
  "extension": [
    {
      "url": "https://bluebutton.cms.gov/resources/variables/race",
      "valueCoding": {
        "system": "https://bluebutton.cms.gov/resources/variables/race",
        "code": "1",
        "display": "White"
      }
    }
  ],
  "identifier": [
    {
      "system": "http://bluebutton.cms.hhs.gov/identifier#bene_id",
      "value": "19990000000162"
    },
    {
      "system": "http://bluebutton.cms.hhs.gov/identifier#hicnHash",
      "value": "d573c3036d561e4975206bb536fe1d813b1fa27386661ef95688814d313aedc0"
    }
  ],
  "name": [
    {
      "use": "usual",
      "family": "Doe",
      "given": [
        "John",
        "X"
      ]
    }
  ],
  "gender": "unknown",
  "birthDate": "1999-06-01",
  "address": [
    {
      "district": "999",
      "state": "22",
      "postalCode": "99999"
    }
  ]
}