{
  "resourceType": "Patient",
  "id": "19990000000644",
  "extension": [
    {
      "url": "https://bluebutton.cms.gov/resources/variables/race",
      "valueCoding": {
        "system": "https://bluebutton.cms.gov/resources/variables/race",
        "code": "1",
        "display": "White"
      }
    }
  ],
  "identifier": [
    {
      "system": "http://bluebutton.cms.hhs.gov/identifier#bene_id",
      "value": "19990000000644"
    },
    {
      "system": "http://bluebutton.cms.hhs.gov/identifier#hicnHash",
      "value": "1ee6248fd3cd0175baa0397b4a4b4020aa0681b96da22aefc5e0d7e960359d02"
    }
  ],
  "name": [
    {
      "use": "usual",
      "family": "Doe",
      "given": [
        "Jane",
        "X"
      ]
    }
  ],
  "gender": "unknown",
  "birthDate": "1999-06-01",
  "address": [
    {
      "district": "999",
      "state": "33",
      "postalCode": "99999"
    }
  ]
}