{
  "resourceType": "Patient",
  "id": "20000000000033",
  "extension": [
    {
      "url": "https://bluebutton.cms.gov/resources/variables/race",
      "valueCoding": {
        "system": "https://bluebutton.cms.gov/resources/variables/race",
        "code": "1",
        "display": "White"
      }
    }
  ],
  "identifier": [
    {
      "system": "http://bluebutton.cms.hhs.gov/identifier#bene_id",
      "value": "20000000000033"
    },
    {
      "system": "http://bluebutton.cms.hhs.gov/identifier#hicnHash",
      "value": "8c802f20081e42725f781f28fb53250c471f09a8b4c6e9774d9eda044357dbce"
    }
  ],
  "name": [
    {
      "use": "usual",
      "family": "Doe",
      "given": [
        "John",
        "X"
      ]
    }
  ],
  "gender": "unknown",
  "birthDate": "2000-06-01",
  "address": [
    {
      "district": "999",
      "state": "30",
      "postalCode": "99999"
    }
  ]
}