{
  "resourceType": "Patient",
  "id": "20000000000722",
  "extension": [
    {
      "url": "https://bluebutton.cms.gov/resources/variables/race",
      "valueCoding": {
        "system": "https://bluebutton.cms.gov/resources/variables/race",
        "code": "1",
        "display": "White"
      }
    }
  ],
  "identifier": [
    {
      "system": "http://bluebutton.cms.hhs.gov/identifier#bene_id",
      "value": "20000000000722"
    },
    {
      "system": "http://bluebutton.cms.hhs.gov/identifier#hicnHash",
      "value": "536768e46f15bba97f773ecc5ab3cb80bb3c1521f519f9a1052bafff715cba18"
    }
  ],
  "name": [
    {
      "use": "usual",
      "family": "Doe",
      "given": [
        "Jane",
        "X"
      ]
    }
  ],
  "gender": "unknown",
  "birthDate": "2000-06-01",
  "address": [
    {
      "district": "999",
      "state": "34",
      "postalCode": "99999"
    }
  ]
}