{
  "resourceType": "Patient",
  "id": "20000000000487",
  "extension": [
    {
      "url": "https://bluebutton.cms.gov/resources/variables/race",
      "valueCoding": {
        "system": "https://bluebutton.cms.gov/resources/variables/race",
        "code": "1",
        "display": "White"
      }
    }
  ],
  "identifier": [
    {
      "system": "http://bluebutton.cms.hhs.gov/identifier#bene_id",
      "value": "20000000000487"
    },
    {
      "system": "http://bluebutton.cms.hhs.gov/identifier#hicnHash",
      "value": "a4fa97fe91857109c8930bf71bb0fc5e46f24f5953d707fc03e839840bf1110e"
    }
  ],
  "name": [
    {
      "use": "usual",
      "family": "Doe",
      "given": [
        "Jane",
        "X"
      ]
    }
  ],
  "gender": "unknown",
  "birthDate": "2000-06-01",
  "address": [
    {
      "district": "999",
      "state": "33",
      "postalCode": "99999"
    }
  ]
}