{
  "resourceType": "Patient",
  "id": "20000000000852",
  "extension": [
    {
      "url": "https://bluebutton.cms.gov/resources/variables/race",
      "valueCoding": {
        "system": "https://bluebutton.cms.gov/resources/variables/race",
        "code": "1",
        "display": "White"
      }
    }
  ],
  "identifier": [
    {
      "system": "http://bluebutton.cms.hhs.gov/identifier#bene_id",
      "value": "20000000000852"
    },
    {
      "system": "http://bluebutton.cms.hhs.gov/identifier#hicnHash",
      "value": "54e3c58b75736d9213de879676550d491af23f350753ed36b646e85fed5d413e"
    }
  ],
  "name": [
    {
      "use": "usual",
      "family": "Doe",
      "given": [
        "Jane",
        "X"
      ]
    }
  ],
  "gender": "unknown",
  "birthDate": "2000-06-01",
  "address": [
    {
      "district": "999",
      "state": "14",
      "postalCode": "99999"
    }
  ]
}