{
  "resourceType": "Patient",
  "id": "20000000000525",
  "extension": [
    {
      "url": "https://bluebutton.cms.gov/resources/variables/race",
      "valueCoding": {
        "system": "https://bluebutton.cms.gov/resources/variables/race",
        "code": "1",
        "display": "White"
      }
    }
  ],
  "identifier": [
    {
      "system": "http://bluebutton.cms.hhs.gov/identifier#bene_id",
      "value": "20000000000525"
    },
    {
      "system": "http://bluebutton.cms.hhs.gov/identifier#hicnHash",
      "value": "6d81145ba259a3623da8833a7ce232f602b21fa476b5a019cb9b853a889b0b28"
    }
  ],
  "name": [
    {
      "use": "usual",
      "family": "Doe",
      "given": [
        "John",
        "X"
      ]
    }
  ],
  "gender": "unknown",
  "birthDate": "2000-06-01",
  "address": [
    {
      "district": "999",
      "state": "34",
      "postalCode": "99999"
    }
  ]
}