{
  "resourceType": "Patient",
  "id": "20140000000215",
  "extension": [
    {
      "url": "https://bluebutton.cms.gov/resources/variables/race",
      "valueCoding": {
        "system": "https://bluebutton.cms.gov/resources/variables/race",
        "code": "1",
        "display": "White"
      }
    }
  ],
  "identifier": [
    {
      "system": "http://bluebutton.cms.hhs.gov/identifier#bene_id",
      "value": "20140000000215"
    },
    {
      "system": "http://bluebutton.cms.hhs.gov/identifier#hicnHash",
      "value": "20155f4b98570ff862143d72e1096fa9a2eafe11d5ece5bea19b0cf47b8264d7"
    }
  ],
  "name": [
    {
      "use": "usual",
      "family": "Doe",
      "given": [
        "John",
        "X"
      ]
    }
  ],
  "gender": "unknown",
  "birthDate": "2014-06-01",
  "address": [
    {
      "district": "999",
      "state": "34",
      "postalCode": "99999"
    }
  ]
}