{
  "resourceType": "Patient",
  "id": "20140000000814",
  "extension": [
    {
      "url": "https://bluebutton.cms.gov/resources/variables/race",
      "valueCoding": {
        "system": "https://bluebutton.cms.gov/resources/variables/race",
        "code": "5",
        "display": "Hispanic"
      }
    }
  ],
  "identifier": [
    {
      "system": "http://bluebutton.cms.hhs.gov/identifier#bene_id",
      "value": "20140000000814"
    },
    {
      "system": "http://bluebutton.cms.hhs.gov/identifier#hicnHash",
      "value": "9c127d199dcf1329faf42fbf3b4141715685f0584df0cd9266e8f0b8732aabfd"
    }
  ],
  "name": [
    {
      "use": "usual",
      "family": "Doe",
      "given": [
        "Jane",
        "X"
      ]
    }
  ],
  "gender": "unknown",
  "birthDate": "2014-06-01",
  "address": [
    {
      "district": "999",
      "state": "33",
      "postalCode": "99999"
    }
  ]
}