{
  "resourceType": "Patient",
  "id": "20140000000799",
  "extension": [
    {
      "url": "https://bluebutton.cms.gov/resources/variables/race",
      "valueCoding": {
        "system": "https://bluebutton.cms.gov/resources/variables/race",
        "code": "1",
        "display": "White"
      }
    }
  ],
  "identifier": [
    {
      "system": "http://bluebutton.cms.hhs.gov/identifier#bene_id",
      "value": "20140000000799"
    },
    {
      "system": "http://bluebutton.cms.hhs.gov/identifier#hicnHash",
      "value": "7bc80f495604f1a3fb38f4dc30afba48e5da4889c26f98de695177a3e071666c"
    }
  ],
  "name": [
    {
      "use": "usual",
      "family": "Doe",
      "given": [
        "Jane",
        "X"
      ]
    }
  ],
  "gender": "unknown",
  "birthDate": "2014-06-01",
  "address": [
    {
      "district": "999",
      "state": "16",
      "postalCode": "99999"
    }
  ]
}