{
  "resourceType": "Patient",
  "id": "20140000000878",
  "extension": [
    {
      "url": "https://bluebutton.cms.gov/resources/variables/race",
      "valueCoding": {
        "system": "https://bluebutton.cms.gov/resources/variables/race",
        "code": "1",
        "display": "White"
      }
    }
  ],
  "identifier": [
    {
      "system": "http://bluebutton.cms.hhs.gov/identifier#bene_id",
      "value": "20140000000878"
    },
    {
      "system": "http://bluebutton.cms.hhs.gov/identifier#hicnHash",
      "value": "3bba1563a9e145727cffdf567a74b1a92863e7ae420cb6d5dee3cca8d054f078"
    }
  ],
  "name": [
    {
      "use": "usual",
      "family": "Doe",
      "given": [
        "John",
        "X"
      ]
    }
  ],
  "gender": "unknown",
  "birthDate": "2014-06-01",
  "address": [
    {
      "district": "999",
      "state": "39",
      "postalCode": "99999"
    }
  ]
}